s3_sc/__init__.py
s3_sc/cli.py
s3_sc/config_reader.py
s3_sc/logger.py
s3_sc/main.py
s3_sc/s3_client.py
s3_sc-1.0.0.dist-info/METADATA
s3_sc-1.0.0.dist-info/WHEEL
s3_sc-1.0.0.dist-info/entry_points.txt
s3_sc-1.0.0.dist-info/RECORD
