Metadata-Version: 2.1
Name: s3_sc
Version: 1.0.0
Summary: S3 simple client
License: MIT
Author: Trusikhin Andrei
Author-email: andrei.trusikhin@gmail.com
Requires-Python: >=3.8
Classifier: Intended Audience :: Developers
Classifier: License :: OSI Approved :: MIT License
Classifier: Operating System :: OS Independent
Classifier: Programming Language :: Python :: 3
Classifier: Programming Language :: Python :: 3.8
Classifier: Programming Language :: Python :: 3.9
Classifier: Programming Language :: Python :: 3.10
Classifier: Programming Language :: Python :: 3.11
Classifier: Programming Language :: Python :: 3.12
Classifier: Topic :: Software Development :: Libraries :: Python Modules
Requires-Dist: aiobotocore (==2.13.2)
Requires-Dist: asyncio (==3.4.3)
Project-URL: Documentation, https://github.com/Onder7994/s3_python_client#readme
Project-URL: Homepage, https://github.com/Onder7994/s3_python_client
Project-URL: Repository, https://github.com/Onder7994/s3_python_client
